atlus/__about__.py
atlus/__init__.py
atlus/atlus.py
atlus/objects.py
atlus/resources.py
atlus-1.0.1.dist-info/METADATA
atlus-1.0.1.dist-info/WHEEL
atlus-1.0.1.dist-info/licenses/LICENSE.txt
atlus-1.0.1.dist-info/RECORD
