Metadata-Version: 2.4
Name: atlus
Version: 1.0.1
Summary: Translate raw address strings into the OSM tagging scheme.
Project-URL: Documentation, https://whubsch.github.io/atlus/index.html
Project-URL: Source, https://github.com/whubsch/atlus
Project-URL: Issues, https://github.com/whubsch/atlus/issues
Author-email: Will <wahubsch@gmail.com>
License-Expression: MIT
License-File: LICENSE.txt
Keywords: address,geocoding,mapping,openstreetmap,osm
Classifier: Development Status :: 4 - Beta
Classifier: License :: OSI Approved :: MIT License
Classifier: Programming Language :: Python
Classifier: Programming Language :: Python :: 3 :: Only
Classifier: Programming Language :: Python :: 3.10
Classifier: Programming Language :: Python :: 3.11
Classifier: Programming Language :: Python :: 3.12
Classifier: Programming Language :: Python :: 3.13
Classifier: Programming Language :: Python :: Implementation :: CPython
Classifier: Programming Language :: Python :: Implementation :: PyPy
Classifier: Typing :: Typed
Requires-Python: >=3.10
Requires-Dist: regex>=2024.11.6
Requires-Dist: usaddress>=0.5.15
